[{
  "key": "839064309-X",
  "name": "Bike",
  "person": "https://i.ibb.co/1bhJJtq/peopleicon.png",
  "img": "https://i.ibb.co/YkPzF8Z/bike.png"
}, {
  "key": "073884804-2",
  "name": "Train",
  "person": "https://i.ibb.co/1bhJJtq/peopleicon.png",
  "img": "https://i.ibb.co/vkv1KV5/train.png"
}, {
  "key": "284834702-3",
  "name": "Bus",
  "person": "https://i.ibb.co/1bhJJtq/peopleicon.png",
  "img": "https://i.ibb.co/cQRfyjp/bus.png"
}, {
  "key": "539248564-2",
  "name": "Car",
  "person": "https://i.ibb.co/1bhJJtq/peopleicon.png",
  "img": "https://i.ibb.co/CP2hZYq/car.png"
}]